filedepot/__init__.py
filedepot/mixins.py
filedepot/models.py
filedepot/management/__init__.py
filedepot/management/commands/__init__.py
filedepot/management/commands/filedepot_clean.py
filedepot/migrations/0001_initial.py
filedepot/migrations/__init__.py
django_filedepot-0.1.0.dist-info/METADATA
django_filedepot-0.1.0.dist-info/WHEEL
django_filedepot-0.1.0.dist-info/top_level.txt
django_filedepot-0.1.0.dist-info/RECORD
